{
  "versions": [
    {
      "name": "AMP",
      "id": 8
    },
    {
      "name": "ASV",
      "id": 12
    },
    {
      "name": "BOOKS",
      "id": 31
    },
    {
      "name": "CEB",
      "id": 37
    },
    {
      "name": "ESV",
      "id": 59
    },
    {
      "name": "GNT",
      "id": 68
    },
    {
      "name": "KJV",
      "id": 1
    },
    {
      "name": "MSG",
      "id": 97
    },
    {
      "name": "NASB",
      "id": 100
    },
    {
      "name": "NCV",
      "id": 105
    },
    {
      "name": "NET",
      "id": 107
    },
    {
      "name": "NIRV",
      "id": 110
    },
    {
      "name": "NIV",
      "id": 111
    },
    {
      "name": "NIVUK",
      "id": 113
    },
    {
      "name": "NKJV",
      "id": 114
    },
    {
      "name": "NLT",
      "id": 116
    },
    {
      "name": "RV1885",
      "id": 477
    }
  ],
  "default_version": 111,
  "books": [
    {
      "name": "Genesis",
      "id": "gen"
    },
    {
      "name": "Exodus",
      "id": "exo"
    },
    {
      "name": "Leviticus",
      "id": "lev"
    },
    {
      "name": "Numbers",
      "id": "num"
    },
    {
      "name": "Deuteronomy",
      "id": "deu"
    },
    {
      "name": "Joshua",
      "id": "jos"
    },
    {
      "name": "Judges",
      "id": "jdg"
    },
    {
      "name": "Ruth",
      "id": "rut"
    },
    {
      "name": "1 Samuel",
      "id": "1sa"
    },
    {
      "name": "2 Samuel",
      "id": "2sa"
    },
    {
      "name": "1 Kings",
      "id": "1ki"
    },
    {
      "name": "2 Kings",
      "id": "2ki"
    },
    {
      "name": "1 Chronicles",
      "id": "1ch"
    },
    {
      "name": "2 Chronicles",
      "id": "2ch"
    },
    {
      "name": "Ezra",
      "id": "ezr"
    },
    {
      "name": "Nehemiah",
      "id": "neh"
    },
    {
      "name": "Esther",
      "id": "est"
    },
    {
      "name": "Job",
      "id": "job"
    },
    {
      "name": "Psalm",
      "id": "psa"
    },
    {
      "name": "Proverbs",
      "id": "pro"
    },
    {
      "name": "Ecclesiastes",
      "id": "ecc"
    },
    {
      "name": "Song of Songs",
      "id": "sng"
    },
    {
      "name": "Isaiah",
      "id": "isa"
    },
    {
      "name": "Jeremiah",
      "id": "jer"
    },
    {
      "name": "Lamentations",
      "id": "lam"
    },
    {
      "name": "Ezekiel",
      "id": "ezk"
    },
    {
      "name": "Daniel",
      "id": "dan"
    },
    {
      "name": "Hosea",
      "id": "hos"
    },
    {
      "name": "Joel",
      "id": "jol"
    },
    {
      "name": "Amos",
      "id": "amo"
    },
    {
      "name": "Obadiah",
      "id": "oba"
    },
    {
      "name": "Jonah",
      "id": "jon"
    },
    {
      "name": "Micah",
      "id": "mic"
    },
    {
      "name": "Nahum",
      "id": "nah"
    },
    {
      "name": "Habakkuk",
      "id": "hab"
    },
    {
      "name": "Zephaniah",
      "id": "zep"
    },
    {
      "name": "Haggai",
      "id": "hag"
    },
    {
      "name": "Zechariah",
      "id": "zec"
    },
    {
      "name": "Malachi",
      "id": "mal"
    },
    {
      "name": "Matthew",
      "id": "mat"
    },
    {
      "name": "Mark",
      "id": "mrk"
    },
    {
      "name": "Luke",
      "id": "luk"
    },
    {
      "name": "John",
      "id": "jhn"
    },
    {
      "name": "Acts",
      "id": "act"
    },
    {
      "name": "Romans",
      "id": "rom"
    },
    {
      "name": "1 Corinthians",
      "id": "1co"
    },
    {
      "name": "2 Corinthians",
      "id": "2co"
    },
    {
      "name": "Galatians",
      "id": "gal"
    },
    {
      "name": "Ephesians",
      "id": "eph"
    },
    {
      "name": "Philippians",
      "id": "php"
    },
    {
      "name": "Colossians",
      "id": "col"
    },
    {
      "name": "1 Thessalonians",
      "id": "1th"
    },
    {
      "name": "2 Thessalonians",
      "id": "2th"
    },
    {
      "name": "1 Timothy",
      "id": "1ti"
    },
    {
      "name": "2 Timothy",
      "id": "2ti"
    },
    {
      "name": "Titus",
      "id": "tit"
    },
    {
      "name": "Philemon",
      "id": "phm"
    },
    {
      "name": "Hebrews",
      "id": "heb"
    },
    {
      "name": "James",
      "id": "jas"
    },
    {
      "name": "1 Peter",
      "id": "1pe"
    },
    {
      "name": "2 Peter",
      "id": "2pe"
    },
    {
      "name": "1 John",
      "id": "1jn"
    },
    {
      "name": "2 John",
      "id": "2jn"
    },
    {
      "name": "3 John",
      "id": "3jn"
    },
    {
      "name": "Jude",
      "id": "jud"
    },
    {
      "name": "Revelation",
      "id": "rev"
    }
  ]
}
